molass_pre/Local.py
molass_pre-0.0.2.dist-info/METADATA
molass_pre-0.0.2.dist-info/WHEEL
molass_pre-0.0.2.dist-info/top_level.txt
molass_pre-0.0.2.dist-info/RECORD
